{
"nexml": {
"@about": "#study", 
"@generator": "Open Tree API", 
"@id": "study", 
"@nexml2json": "1.2.1", 
"@nexmljson": "http://purl.org/opentree/nexson", 
"@version": "0.9", 
"@xmlns": {
"$": "http://www.nexml.org/2009", 
"nex": "http://www.nexml.org/2009", 
"ot": "http://purl.org/opentree-terms#", 
"xhtml": "http://www.w3.org/1999/xhtml/vocab#", 
"xsd": "http://www.w3.org/2001/XMLSchema#", 
"xsi": "http://www.w3.org/2001/XMLSchema-instance"
}, 
"^ot:agents": {
"agent": [
{
"@description": "Open Tree NexSON validation", 
"@id": "peyotl-validator", 
"@name": "api.opentreeoflife.org/validate", 
"@url": "https://github.com/OpenTreeOfLife/peyotl", 
"@version": "0.0.4a", 
"invocation": {
"commandLine": [], 
"otherProperty": [
{
"name": "pythonVersion", 
"value": "2.7.9"
}, 
{
"name": "pythonImplementation", 
"value": "CPython"
}
]
}
}, 
{
"@description": "Web-based interface for submitting, editing, and reviewing studies in the Open Tree of Life project.", 
"@id": "opentree-curation-webapp", 
"@name": "OpenTree curation webapp", 
"@url": "https://github.com/OpenTreeOfLife/opentree", 
"@version": "0.0.0"
}
]
}, 
"^ot:annotationEvents": {
"annotation": [
{
"@dateCreated": "2017-10-06T20:58:10.929Z", 
"@description": "Aids for mapping study OTUs to OTT taxa", 
"@id": "otu-mapping-hints", 
"@passedChecks": true, 
"@preserve": true, 
"@wasAssociatedWithAgentId": "opentree-curation-webapp", 
"message": [
{
"@code": "OTU_MAPPING_HINTS", 
"@humanMessageType": "NONE", 
"@severity": "INFO", 
"data": {
"searchContext": {
"$": "Insects"
}, 
"substitutions": {
"substitution": [
{
"@active": false, 
"@valid": true, 
"new": {
"$": ""
}, 
"old": {
"$": ""
}
}
]
}, 
"useFuzzyMatching": false
}, 
"refersTo": {
"@top": {
"$": "meta"
}
}
}
]
}, 
{
"@dateCreated": "2017-10-06T20:58:10.929Z", 
"@description": "Describes supporting data files for this study", 
"@id": "supporting-files-metadata", 
"@passedChecks": true, 
"@preserve": true, 
"@wasAssociatedWithAgentId": "opentree-curation-webapp", 
"message": [
{
"@code": "SUPPORTING_FILE_INFO", 
"@humanMessageType": "NONE", 
"@severity": "INFO", 
"data": {
"@movedToPermanentArchive": false, 
"files": {
"file": [
{
"@filename": "PASTED.tre", 
"@size": 1022, 
"@type": "newick", 
"@url": "/curator/download/supporting_files.doc.9a77e2613b155875.5041535445442e747265.tre", 
"description": {
"$": "Tree in figure 1 of the study"
}, 
"sourceForTree": [
{
"$": "tree1"
}
]
}, 
{
"@filename": "PASTED.tre", 
"@size": 1024, 
"@type": "newick", 
"@url": "/curator/download/supporting_files.doc.84419baf7c498075.5041535445442e747265.tre", 
"description": {
"$": "Source data for tree(s) 'tree1'"
}, 
"sourceForTree": [
{
"$": "tree1"
}
]
}
]
}
}, 
"refersTo": {
"@top": {
"$": "meta"
}
}
}
]
}
]
}, 
"^ot:candidateTreeForSynthesis": [], 
"^ot:comment": "This tree is shown in Fig 1 of the paper, and was based on parsimony using morphology.", 
"^ot:curatorName": [
"Bruno de Medeiros"
], 
"^ot:dataDeposit": {
"@href": ""
}, 
"^ot:focalClade": 5807594, 
"^ot:focalCladeOTTTaxonName": "Catopocerinae", 
"^ot:otusElementOrder": [
"otus1"
], 
"^ot:studyId": "ot_1187", 
"^ot:studyPublication": {
"@href": "http://www.mapress.com/zootaxa/2011/f/zt03077p118.pdf"
}, 
"^ot:studyPublicationReference": "Peck, S.B. & Cook, J. 2011. Systematics, distributions and bionomics of the Catopocerini (eyeless soil fungivore beetles)\nof North America (Coleoptera: Leiodidae: Catopocerinae). Zootaxa 3077:1-118", 
"^ot:studyYear": 2011, 
"^ot:tag": [], 
"^ot:treesElementOrder": [
"trees1"
], 
"otusById": {
"otus1": {
"otuById": {
"otu1": {
"^ot:originalLabel": "Glacicavicola bathyscioides", 
"^ot:ottId": 6520187, 
"^ot:ottTaxonName": "Glacicavicola bathyscioides"
}, 
"otu10": {
"^ot:originalLabel": "Pinodytes capizzii", 
"^ot:ottId": 6520146, 
"^ot:ottTaxonName": "Pinodytes capizzii"
}, 
"otu11": {
"^ot:originalLabel": "Pinodytes gatibaldi", 
"^ot:ottId": 6520153, 
"^ot:ottTaxonName": "Pinodytes gatibaldi"
}, 
"otu12": {
"^ot:originalLabel": "Pinodytes haidagwaii", 
"^ot:ottId": 6259022, 
"^ot:ottTaxonName": "Pinodytes haidagwaii"
}, 
"otu13": {
"^ot:originalLabel": "Pinodytes imbricatus", 
"^ot:ottId": 6520157, 
"^ot:ottTaxonName": "Pinodytes imbricatus"
}, 
"otu14": {
"^ot:originalLabel": "Pinodytes isabella", 
"^ot:ottId": 6520158, 
"^ot:ottTaxonName": "Pinodytes isabella"
}, 
"otu15": {
"^ot:originalLabel": "Pinodytes newelli", 
"^ot:ottId": 5825244, 
"^ot:ottTaxonName": "Pinodytes newelli"
}, 
"otu16": {
"^ot:originalLabel": "Pinodytes orca", 
"^ot:ottId": 6520165, 
"^ot:ottTaxonName": "Pinodytes orca"
}, 
"otu17": {
"^ot:originalLabel": "Pinodytes shoshone", 
"^ot:ottId": 6520175, 
"^ot:ottTaxonName": "Pinodytes shoshone"
}, 
"otu18": {
"^ot:originalLabel": "Pinodytes sinuatus", 
"^ot:ottId": 6520176, 
"^ot:ottTaxonName": "Pinodytes sinuatus"
}, 
"otu19": {
"^ot:originalLabel": "Pinodytes subterraneus", 
"^ot:ottId": 6520178, 
"^ot:ottTaxonName": "Pinodytes subterraneus"
}, 
"otu2": {
"^ot:originalLabel": "Perkovskius ussuriensis", 
"^ot:ottId": 6520188, 
"^ot:ottTaxonName": "Perkovskius ussuriensis"
}, 
"otu20": {
"^ot:originalLabel": "Pinodytes tibialis", 
"^ot:ottId": 6520180, 
"^ot:ottTaxonName": "Pinodytes tibialis"
}, 
"otu21": {
"^ot:originalLabel": "Pinodytes delnorte", 
"^ot:ottId": 5825243, 
"^ot:ottTaxonName": "Pinodytes delnorte"
}, 
"otu22": {
"^ot:originalLabel": "Pinodytes setosus", 
"^ot:ottId": 6520173, 
"^ot:ottTaxonName": "Pinodytes setosus"
}, 
"otu23": {
"^ot:originalLabel": "Pinodytes cryptophagoides", 
"^ot:ottId": 6259021, 
"^ot:ottTaxonName": "Pinodytes cryptophagoides"
}, 
"otu24": {
"^ot:originalLabel": "Pinodytes rothi", 
"^ot:ottId": 6520170, 
"^ot:ottTaxonName": "Pinodytes rothi"
}, 
"otu25": {
"^ot:originalLabel": "Pinodytes borealis", 
"^ot:ottId": 6259020, 
"^ot:ottTaxonName": "Pinodytes borealis"
}, 
"otu26": {
"^ot:originalLabel": "Pinodytes punctuatus", 
"^ot:ottId": 6520168, 
"^ot:ottTaxonName": "Pinodytes punctuatus"
}, 
"otu27": {
"^ot:originalLabel": "Pinodytes colorado", 
"^ot:ottId": 6520148, 
"^ot:ottTaxonName": "Pinodytes colorado"
}, 
"otu28": {
"^ot:originalLabel": "Pinodytes newtoni", 
"^ot:ottId": 6520164, 
"^ot:ottTaxonName": "Pinodytes newtoni"
}, 
"otu29": {
"^ot:originalLabel": "Pinodytes constrictus", 
"^ot:ottId": 6520149, 
"^ot:ottTaxonName": "Pinodytes constrictus"
}, 
"otu3": {
"^ot:originalLabel": "Perkovskius zerchei", 
"^ot:ottId": 6520189, 
"^ot:ottTaxonName": "Perkovskius zerchei"
}, 
"otu30": {
"^ot:originalLabel": "Pinodytes contortus", 
"^ot:ottId": 6520150, 
"^ot:ottTaxonName": "Pinodytes contortus"
}, 
"otu31": {
"^ot:originalLabel": "Pinodytes idaho", 
"^ot:ottId": 6520156, 
"^ot:ottTaxonName": "Pinodytes idaho"
}, 
"otu32": {
"^ot:originalLabel": "Pinodytes klamathensis", 
"^ot:ottId": 6520159, 
"^ot:ottTaxonName": "Pinodytes klamathensis"
}, 
"otu33": {
"^ot:originalLabel": "Pinodytes losangeles", 
"^ot:ottId": 6520160, 
"^ot:ottTaxonName": "Pinodytes losangeles"
}, 
"otu34": {
"^ot:originalLabel": "Pinodytes marinensis", 
"^ot:ottId": 6520161, 
"^ot:ottTaxonName": "Pinodytes marinensis"
}, 
"otu35": {
"^ot:originalLabel": "Pinodytes minutus", 
"^ot:ottId": 6520162, 
"^ot:ottTaxonName": "Pinodytes minutus"
}, 
"otu36": {
"^ot:originalLabel": "Pinodytes monterey", 
"^ot:ottId": 6520163, 
"^ot:ottTaxonName": "Pinodytes monterey"
}, 
"otu37": {
"^ot:originalLabel": "Pinodytes ovatus", 
"^ot:ottId": 6520166, 
"^ot:ottTaxonName": "Pinodytes ovatus"
}, 
"otu38": {
"^ot:originalLabel": "Pinodytes parvus", 
"^ot:ottId": 6520167, 
"^ot:ottTaxonName": "Pinodytes parvus"
}, 
"otu39": {
"^ot:originalLabel": "Pinodytes sanjacinto", 
"^ot:ottId": 6520171, 
"^ot:ottTaxonName": "Pinodytes sanjacinto"
}, 
"otu4": {
"^ot:originalLabel": "Catopocerus alabamae", 
"^ot:ottId": 6520182, 
"^ot:ottTaxonName": "Catopocerus alabamae"
}, 
"otu40": {
"^ot:originalLabel": "Pinodytes spinus", 
"^ot:ottId": 6520177, 
"^ot:ottTaxonName": "Pinodytes spinus"
}, 
"otu41": {
"^ot:originalLabel": "Pinodytes chandleri", 
"^ot:ottId": 6520147, 
"^ot:ottTaxonName": "Pinodytes chandleri"
}, 
"otu42": {
"^ot:originalLabel": "Pinodytes humboldtensis", 
"^ot:ottId": 6520155, 
"^ot:ottTaxonName": "Pinodytes humboldtensis"
}, 
"otu43": {
"^ot:originalLabel": "Pinodytes shasta", 
"^ot:ottId": 6520174, 
"^ot:ottTaxonName": "Pinodytes shasta"
}, 
"otu44": {
"^ot:originalLabel": "Pinodytes tehama", 
"^ot:ottId": 6520179, 
"^ot:ottTaxonName": "Pinodytes tehama"
}, 
"otu45": {
"^ot:originalLabel": "Pinodytes fresno", 
"^ot:ottId": 6520152, 
"^ot:ottTaxonName": "Pinodytes fresno"
}, 
"otu46": {
"^ot:originalLabel": "Pinodytes gibbosus", 
"^ot:ottId": 6520154, 
"^ot:ottTaxonName": "Pinodytes gibbosus"
}, 
"otu47": {
"^ot:originalLabel": "Pinodytes pusio", 
"^ot:ottId": 6520169, 
"^ot:ottTaxonName": "Pinodytes pusio"
}, 
"otu48": {
"^ot:originalLabel": "Pinodytes tuolumne", 
"^ot:ottId": 6520181, 
"^ot:ottTaxonName": "Pinodytes tuolumne"
}, 
"otu49": {
"^ot:originalLabel": "Pinodytes eldorado", 
"^ot:ottId": 6520151, 
"^ot:ottTaxonName": "Pinodytes eldorado"
}, 
"otu5": {
"^ot:originalLabel": "Catopocerus appalachianus", 
"^ot:ottId": 6520183, 
"^ot:ottTaxonName": "Catopocerus appalachianus"
}, 
"otu50": {
"^ot:originalLabel": "Pinodytes sequoia", 
"^ot:ottId": 6520172, 
"^ot:ottTaxonName": "Pinodytes sequoia"
}, 
"otu6": {
"^ot:originalLabel": "Catopocerus hamiltoni", 
"^ot:ottId": 6520184, 
"^ot:ottTaxonName": "Catopocerus hamiltoni"
}, 
"otu7": {
"^ot:originalLabel": "Catopocerus jonesi", 
"^ot:ottId": 6520185, 
"^ot:ottTaxonName": "Catopocerus jonesi"
}, 
"otu8": {
"^ot:originalLabel": "Catopocerus politus", 
"^ot:ottId": 6520186, 
"^ot:ottTaxonName": "Catopocerus politus"
}, 
"otu9": {
"^ot:originalLabel": "Pinodytes angulatus", 
"^ot:ottId": 6520145, 
"^ot:ottTaxonName": "Pinodytes angulatus"
}
}
}
}, 
"treesById": {
"trees1": {
"@otus": "otus1", 
"^ot:treeElementOrder": [
"tree1"
], 
"treeById": {
"tree1": {
"@label": "morphological tree", 
"@xsi:type": "nex:FloatTree", 
"^ot:branchLengthDescription": "", 
"^ot:branchLengthMode": "ot:undefined", 
"^ot:curatedType": "Maximum parsimony ", 
"^ot:inGroupClade": "node6", 
"^ot:nodeLabelMode": "", 
"^ot:nodeLabelTimeUnit": "", 
"^ot:outGroupEdge": "", 
"^ot:reasonsToExcludeFromSynthesis": [], 
"^ot:rootNodeId": "tree1_ROOT", 
"^ot:specifiedRoot": "tree1_ROOT", 
"^ot:tag": [
"morphology"
], 
"^ot:unrootedTree": false, 
"edgeBySourceId": {
"node1": {
"edge2": {
"@source": "node1", 
"@target": "node3"
}, 
"edge5": {
"@source": "node1", 
"@target": "node6"
}
}, 
"node10": {
"edge10": {
"@source": "node10", 
"@target": "node11"
}, 
"edge11": {
"@source": "node10", 
"@target": "node12"
}, 
"edge12": {
"@source": "node10", 
"@target": "node13"
}
}, 
"node14": {
"edge14": {
"@source": "node14", 
"@target": "node15"
}, 
"edge33": {
"@source": "node14", 
"@target": "node34"
}
}, 
"node15": {
"edge15": {
"@source": "node15", 
"@target": "node16"
}, 
"edge16": {
"@source": "node15", 
"@target": "node17"
}, 
"edge17": {
"@source": "node15", 
"@target": "node18"
}, 
"edge18": {
"@source": "node15", 
"@target": "node19"
}, 
"edge19": {
"@source": "node15", 
"@target": "node20"
}, 
"edge20": {
"@source": "node15", 
"@target": "node21"
}, 
"edge21": {
"@source": "node15", 
"@target": "node22"
}, 
"edge22": {
"@source": "node15", 
"@target": "node23"
}, 
"edge23": {
"@source": "node15", 
"@target": "node24"
}, 
"edge24": {
"@source": "node15", 
"@target": "node25"
}, 
"edge25": {
"@source": "node15", 
"@target": "node26"
}, 
"edge26": {
"@source": "node15", 
"@target": "node27"
}, 
"edge27": {
"@source": "node15", 
"@target": "node28"
}
}, 
"node28": {
"edge28": {
"@source": "node28", 
"@target": "node29"
}, 
"edge29": {
"@source": "node28", 
"@target": "node30"
}, 
"edge30": {
"@source": "node28", 
"@target": "node31"
}
}, 
"node3": {
"edge3": {
"@source": "node3", 
"@target": "node4"
}, 
"edge4": {
"@source": "node3", 
"@target": "node5"
}
}, 
"node31": {
"edge31": {
"@source": "node31", 
"@target": "node32"
}, 
"edge32": {
"@source": "node31", 
"@target": "node33"
}
}, 
"node34": {
"edge34": {
"@source": "node34", 
"@target": "node35"
}, 
"edge35": {
"@source": "node34", 
"@target": "node36"
}
}, 
"node36": {
"edge36": {
"@source": "node36", 
"@target": "node37"
}, 
"edge37": {
"@source": "node36", 
"@target": "node38"
}
}, 
"node38": {
"edge38": {
"@source": "node38", 
"@target": "node39"
}, 
"edge39": {
"@source": "node38", 
"@target": "node40"
}, 
"edge40": {
"@source": "node38", 
"@target": "node41"
}
}, 
"node41": {
"edge41": {
"@source": "node41", 
"@target": "node42"
}, 
"edge42": {
"@source": "node41", 
"@target": "node43"
}, 
"edge43": {
"@source": "node41", 
"@target": "node44"
}, 
"edge44": {
"@source": "node41", 
"@target": "node45"
}, 
"edge45": {
"@source": "node41", 
"@target": "node46"
}, 
"edge46": {
"@source": "node41", 
"@target": "node47"
}, 
"edge47": {
"@source": "node41", 
"@target": "node48"
}, 
"edge48": {
"@source": "node41", 
"@target": "node49"
}, 
"edge49": {
"@source": "node41", 
"@target": "node50"
}, 
"edge50": {
"@source": "node41", 
"@target": "node51"
}, 
"edge51": {
"@source": "node41", 
"@target": "node52"
}, 
"edge52": {
"@source": "node41", 
"@target": "node53"
}, 
"edge53": {
"@source": "node41", 
"@target": "node54"
}
}, 
"node54": {
"edge54": {
"@source": "node54", 
"@target": "node55"
}, 
"edge59": {
"@source": "node54", 
"@target": "node60"
}
}, 
"node55": {
"edge55": {
"@source": "node55", 
"@target": "node56"
}, 
"edge56": {
"@source": "node55", 
"@target": "node57"
}, 
"edge57": {
"@source": "node55", 
"@target": "node58"
}, 
"edge58": {
"@source": "node55", 
"@target": "node59"
}
}, 
"node6": {
"edge13": {
"@source": "node6", 
"@target": "node14"
}, 
"edge6": {
"@source": "node6", 
"@target": "node7"
}
}, 
"node60": {
"edge60": {
"@source": "node60", 
"@target": "node61"
}, 
"edge61": {
"@source": "node60", 
"@target": "node62"
}, 
"edge62": {
"@source": "node60", 
"@target": "node63"
}, 
"edge63": {
"@source": "node60", 
"@target": "node64"
}, 
"edge64": {
"@source": "node60", 
"@target": "node65"
}
}, 
"node65": {
"edge65": {
"@source": "node65", 
"@target": "node66"
}, 
"edge66": {
"@source": "node65", 
"@target": "node67"
}
}, 
"node7": {
"edge7": {
"@source": "node7", 
"@target": "node8"
}, 
"edge8": {
"@source": "node7", 
"@target": "node9"
}, 
"edge9": {
"@source": "node7", 
"@target": "node10"
}
}, 
"tree1_ROOT": {
"edge1": {
"@source": "tree1_ROOT", 
"@target": "node2"
}, 
"tree1_ROOT_EDGE": {
"@source": "tree1_ROOT", 
"@target": "node1"
}
}
}, 
"nodeById": {
"node1": {}, 
"node10": {}, 
"node11": {
"@otu": "otu6"
}, 
"node12": {
"@otu": "otu7"
}, 
"node13": {
"@otu": "otu8"
}, 
"node14": {}, 
"node15": {}, 
"node16": {
"@otu": "otu9"
}, 
"node17": {
"@otu": "otu10"
}, 
"node18": {
"@otu": "otu11"
}, 
"node19": {
"@otu": "otu12"
}, 
"node2": {
"@otu": "otu1"
}, 
"node20": {
"@otu": "otu13"
}, 
"node21": {
"@otu": "otu14"
}, 
"node22": {
"@otu": "otu15"
}, 
"node23": {
"@otu": "otu16"
}, 
"node24": {
"@otu": "otu17"
}, 
"node25": {
"@otu": "otu18"
}, 
"node26": {
"@otu": "otu19"
}, 
"node27": {
"@otu": "otu20"
}, 
"node28": {}, 
"node29": {
"@otu": "otu21"
}, 
"node3": {}, 
"node30": {
"@otu": "otu22"
}, 
"node31": {}, 
"node32": {
"@otu": "otu23"
}, 
"node33": {
"@otu": "otu24"
}, 
"node34": {}, 
"node35": {
"@otu": "otu25"
}, 
"node36": {}, 
"node37": {
"@otu": "otu26"
}, 
"node38": {}, 
"node39": {
"@otu": "otu27"
}, 
"node4": {
"@otu": "otu2"
}, 
"node40": {
"@otu": "otu28"
}, 
"node41": {}, 
"node42": {
"@otu": "otu29"
}, 
"node43": {
"@otu": "otu30"
}, 
"node44": {
"@otu": "otu31"
}, 
"node45": {
"@otu": "otu32"
}, 
"node46": {
"@otu": "otu33"
}, 
"node47": {
"@otu": "otu34"
}, 
"node48": {
"@otu": "otu35"
}, 
"node49": {
"@otu": "otu36"
}, 
"node5": {
"@otu": "otu3"
}, 
"node50": {
"@otu": "otu37"
}, 
"node51": {
"@otu": "otu38"
}, 
"node52": {
"@otu": "otu39"
}, 
"node53": {
"@otu": "otu40"
}, 
"node54": {}, 
"node55": {}, 
"node56": {
"@otu": "otu41"
}, 
"node57": {
"@otu": "otu42"
}, 
"node58": {
"@otu": "otu43"
}, 
"node59": {
"@otu": "otu44"
}, 
"node6": {}, 
"node60": {}, 
"node61": {
"@otu": "otu45"
}, 
"node62": {
"@otu": "otu46"
}, 
"node63": {
"@otu": "otu47"
}, 
"node64": {
"@otu": "otu48"
}, 
"node65": {}, 
"node66": {
"@otu": "otu49"
}, 
"node67": {
"@otu": "otu50"
}, 
"node7": {}, 
"node8": {
"@otu": "otu4"
}, 
"node9": {
"@otu": "otu5"
}, 
"tree1_ROOT": {
"@root": true
}
}
}
}
}
}
}
}
